<?xml version="1.0" encoding="utf-8" ?>
<dwsync>
<file name="jquery.bootstrap.js" server="ftp.cafebarragrande.com.br" local="131016281760000000" remote="131212106400000000" Dst="2" />
<file name="jquery.color.js" server="ftp.cafebarragrande.com.br" local="130933564580000000" remote="131212106400000000" Dst="2" />
<file name="jquery.chart.js" server="ftp.cafebarragrande.com.br" local="130933565160000000" remote="131212106400000000" Dst="2" />
<file name="jquery.cookie.js" server="ftp.cafebarragrande.com.br" local="130933558640000000" remote="131212106400000000" Dst="2" />
<file name="jquery.countdown.js" server="ftp.cafebarragrande.com.br" local="130933560920000000" remote="131212106400000000" Dst="2" />
<file name="jquery.countto.js" server="ftp.cafebarragrande.com.br" local="130933563300000000" remote="131212106400000000" Dst="2" />
<file name="jquery.dribbble.js" server="ftp.cafebarragrande.com.br" local="130933558240000000" remote="131212106400000000" Dst="2" />
<file name="jquery.fitvids.js" server="ftp.cafebarragrande.com.br" local="130933547760000000" remote="131212106400000000" Dst="2" />
<file name="jquery.flexslider.js" server="ftp.cafebarragrande.com.br" local="131016283600000000" remote="131212106400000000" Dst="2" />
<file name="jquery.flickrfeed.js" server="ftp.cafebarragrande.com.br" local="130933557580000000" remote="131212106400000000" Dst="2" />
<file name="jquery.form.js" server="ftp.cafebarragrande.com.br" local="130933565600000000" remote="131212106400000000" Dst="2" />
<file name="jquery.important.js" server="ftp.cafebarragrande.com.br" local="131016281340000000" remote="131212106400000000" Dst="2" />
<file name="jquery.infinitescroll.js" server="ftp.cafebarragrande.com.br" local="130933579920000000" remote="131212106400000000" Dst="2" />
<file name="jquery.instagram.js" server="ftp.cafebarragrande.com.br" local="131016284820000000" remote="131212106400000000" Dst="2" />
<file name="jquery.magnific.js" server="ftp.cafebarragrande.com.br" local="131016285140000000" remote="131212106400000000" Dst="2" />
<file name="jquery.isotope.js" server="ftp.cafebarragrande.com.br" local="131113325900000000" remote="131212106400000000" Dst="2" />
<file name="jquery.pagetransition.js" server="ftp.cafebarragrande.com.br" local="130933560500000000" remote="131212106400000000" Dst="2" />
<file name="jquery.owlcarousel.js" server="ftp.cafebarragrande.com.br" local="131016285360000000" remote="131212106400000000" Dst="2" />
<file name="jquery.paginate.js" server="ftp.cafebarragrande.com.br" local="130933579700000000" remote="131212106400000000" Dst="2" />
<file name="jquery.parallax.js" server="ftp.cafebarragrande.com.br" local="130933560680000000" remote="131212106400000000" Dst="2" />
<file name="jquery.piechart.js" server="ftp.cafebarragrande.com.br" local="130933559580000000" remote="131212107000000000" Dst="2" />
<file name="jquery.superfish.js" server="ftp.cafebarragrande.com.br" local="131016286100000000" remote="131212107000000000" Dst="2" />
<file name="jquery.tabs.js" server="ftp.cafebarragrande.com.br" local="131016286740000000" remote="131212107000000000" Dst="2" />
<file name="jquery.swiper.js" server="ftp.cafebarragrande.com.br" local="131016286240000000" remote="131212107000000000" Dst="2" />
<file name="jquery.toastr.js" server="ftp.cafebarragrande.com.br" local="131016287000000000" remote="131212107000000000" Dst="2" />
<file name="jquery.textrotator.js" server="ftp.cafebarragrande.com.br" local="131016285640000000" remote="131212107000000000" Dst="2" />
<file name="jquery.twitterfeed.js" server="ftp.cafebarragrande.com.br" local="131016287220000000" remote="131212107000000000" Dst="2" />
<file name="jquery.validation.js" server="ftp.cafebarragrande.com.br" local="131016287480000000" remote="131212107000000000" Dst="2" />
<file name="jquery.youtube.js" server="ftp.cafebarragrande.com.br" local="131016287700000000" remote="131212107000000000" Dst="2" />
</dwsync>