<?xml version="1.0" encoding="utf-8" ?>
<dwsync>
<file name="02.png" server="ftp.cafebarragrande.com.br" local="131181584300000000" remote="131212103400000000" Dst="2" />
<file name="01.png" server="ftp.cafebarragrande.com.br" local="131181583920000000" remote="131212103400000000" Dst="2" />
<file name="03.png" server="ftp.cafebarragrande.com.br" local="131181586710000000" remote="131212103400000000" Dst="2" />
<file name="05.png" server="ftp.cafebarragrande.com.br" local="131181588840000000" remote="131212103400000000" Dst="2" />
<file name="06.png" server="ftp.cafebarragrande.com.br" local="131181589120000000" remote="131212103400000000" Dst="2" />
<file name="07.png" server="ftp.cafebarragrande.com.br" local="131181589780000000" remote="131212104000000000" Dst="2" />
<file name="08.png" server="ftp.cafebarragrande.com.br" local="131181590130000000" remote="131212104000000000" Dst="2" />
<file name="09.png" server="ftp.cafebarragrande.com.br" local="131181590680000000" remote="131212104000000000" Dst="2" />
<file name="11.png" server="ftp.cafebarragrande.com.br" local="131181591450000000" remote="131212104000000000" Dst="2" />
<file name="10.png" server="ftp.cafebarragrande.com.br" local="131181590850000000" remote="131212104600000000" Dst="2" />
<file name="12.png" server="ftp.cafebarragrande.com.br" local="131181591810000000" remote="131212104600000000" Dst="2" />
<file name="13.png" server="ftp.cafebarragrande.com.br" local="131181595050000000" remote="131212104600000000" Dst="2" />
<file name="14.png" server="ftp.cafebarragrande.com.br" local="131181595460000000" remote="131212104600000000" Dst="2" />
<file name="15.png" server="ftp.cafebarragrande.com.br" local="131181595820000000" remote="131212104600000000" Dst="2" />
<file name="16.png" server="ftp.cafebarragrande.com.br" local="131181596470000000" remote="131212104600000000" Dst="2" />
<file name="17.png" server="ftp.cafebarragrande.com.br" local="131181596770000000" remote="131212104600000000" Dst="2" />
<file name="18.png" server="ftp.cafebarragrande.com.br" local="131181597320000000" remote="131212104600000000" Dst="2" />
<file name="21.png" server="ftp.cafebarragrande.com.br" local="131284844227051725" remote="131284673400000000" Dst="2" />
<file name="19.png" server="ftp.cafebarragrande.com.br" local="131284842463331141" remote="131284673400000000" Dst="2" />
<file name="20.png" server="ftp.cafebarragrande.com.br" local="131284843468241062" remote="131284673400000000" Dst="2" />
<file name="22.png" server="ftp.cafebarragrande.com.br" local="131284844784968034" remote="131284673400000000" Dst="2" />
<file name="24.png" server="ftp.cafebarragrande.com.br" local="131284845828651839" remote="131284673400000000" Dst="2" />
<file name="23.png" server="ftp.cafebarragrande.com.br" local="131284845311431395" remote="131284673400000000" Dst="2" />
<file name="25.png" server="ftp.cafebarragrande.com.br" local="131284846355546491" remote="131284674000000000" Dst="2" />
<file name="27.png" server="ftp.cafebarragrande.com.br" local="131284847392060304" remote="131284674000000000" Dst="2" />
<file name="26.png" server="ftp.cafebarragrande.com.br" local="131284846844009019" remote="131284674000000000" Dst="2" />
<file name="28.png" server="ftp.cafebarragrande.com.br" local="131284848623213250" remote="131284674000000000" Dst="2" />
<file name="29.png" server="ftp.cafebarragrande.com.br" local="131284847871326763" remote="131284674000000000" Dst="2" />
<file name="30.png" server="ftp.cafebarragrande.com.br" local="131284849159575771" remote="131284674000000000" Dst="2" />
</dwsync>